ankisync2/__init__.py
ankisync2/anki20/__init__.py
ankisync2/anki20/builder.py
ankisync2/anki20/db.py
ankisync2/anki21/__init__.py
ankisync2/anki21/db.py
ankisync2/ankiconnect.py
ankisync2/apkg.py
ankisync2/dir.py
ankisync2/fields.py
ankisync2/util.py
ankisync2-0.3.4.dist-info/LICENSE
ankisync2-0.3.4.dist-info/WHEEL
ankisync2-0.3.4.dist-info/METADATA
ankisync2-0.3.4.dist-info/RECORD
