Metadata-Version: 2.1
Name: ankisync2
Version: 0.3.4
Summary: Creating and editing *.apkg and *.anki2 safely
Home-page: https://github.com/patarapolw/ankisync2
License: MIT
Keywords: anki,srs,memorization,spaced-repetition,anki-flashcards
Author: Pacharapol Withayasakpunt
Author-email: patarapolw@gmail.com
Requires-Python: >=3.7,<4.0
Classifier: License :: OSI Approved :: MIT License
Classifier: Programming Language :: Python :: 3
Classifier: Programming Language :: Python :: 3.10
Classifier: Programming Language :: Python :: 3.7
Classifier: Programming Language :: Python :: 3.8
Classifier: Programming Language :: Python :: 3.9
Requires-Dist: peewee (>=3.9,<4.0)
Requires-Dist: semver (>=2.13.0,<3.0.0)
Requires-Dist: shortuuid (>=0.5.0,<0.6.0)
Project-URL: Repository, https://github.com/patarapolw/ankisync2
